overture_song/__init__.py
overture_song/client.py
overture_song/entities.py
overture_song/model.py
overture_song/rest.py
overture_song/tools.py
overture_song/utils.py
overture_song/validation.py
overture_song-5.0.0.dist-info/LICENSE.txt
overture_song-5.0.0.dist-info/METADATA
overture_song-5.0.0.dist-info/WHEEL
overture_song-5.0.0.dist-info/top_level.txt
overture_song-5.0.0.dist-info/RECORD
