Metadata-Version: 2.1
Name: overture-song
Version: 5.0.0
Summary: A Python library interface to the SONG REST Server
Home-page: https://github.com/overture-stack/SONG
Author: Robert Tisma
Author-email: Robert.Tisma@oicr.on.ca
Maintainer: Leonardo Rivera
Maintainer-email: lrivera@oicr.on.ca
License: License :: OSI Approved :: GNU General Public License v3 (GPLv3)
Keywords: overture_song rest-client python-sdk song metadata
Classifier: Development Status :: 3 - Alpha
Classifier: Intended Audience :: Developers
Classifier: License :: OSI Approved :: GNU General Public License v3 (GPLv3)
Classifier: Programming Language :: Python :: 2
Classifier: Programming Language :: Python :: 3
Requires-Python: >=3.6.0
License-File: LICENSE.txt
Requires-Dist: requests (>=2.20.0)
Requires-Dist: dataclasses (>=0.4)
